README.md
setup.py
watch_do/__init__.py
watch_do/banner_builder.py
watch_do/cli.py
watch_do/doer_manager.py
watch_do/exceptions.py
watch_do/glob_manager.py
watch_do/watcher_manager.py
watch_do.egg-info/PKG-INFO
watch_do.egg-info/SOURCES.txt
watch_do.egg-info/dependency_links.txt
watch_do.egg-info/entry_points.txt
watch_do.egg-info/top_level.txt
watch_do/doers/__init__.py
watch_do/doers/doer.py
watch_do/doers/shell.py
watch_do/watchers/__init__.py
watch_do/watchers/hash.py
watch_do/watchers/stat.py
watch_do/watchers/watcher.py